evrmore/__init__.py
evrmore/assets.py
evrmore/base58.py
evrmore/bech32.py
evrmore/bloom.py
evrmore/crypto.py
evrmore/messages.py
evrmore/net.py
evrmore/rpc.py
evrmore/segwit_addr.py
evrmore/signature.py
evrmore/signmessage.py
evrmore/wallet.py
evrmore/blockchain/__init__.py
evrmore/blockchain/index.py
evrmore/blockchain/utils.py
evrmore/core/__init__.py
evrmore/core/_bignum.py
evrmore/core/assets.py
evrmore/core/key.py
evrmore/core/script.py
evrmore/core/scripteval.py
evrmore/core/serialize.py
evrmore/core/transaction.py
evrmore/tests/__init__.py
evrmore/tests/fakeravencoinproxy.py
evrmore/tests/manual_evrmore_test.py
evrmore/tests/test_asset_script.py
evrmore/tests/test_assets.py
evrmore/tests/test_base58.py
evrmore/tests/test_bech32.py
evrmore/tests/test_bloom.py
evrmore/tests/test_checkblock.py
evrmore/tests/test_core.py
evrmore/tests/test_fakeravencoinproxy.py
evrmore/tests/test_key.py
evrmore/tests/test_messages.py
evrmore/tests/test_messaging.py
evrmore/tests/test_net.py
evrmore/tests/test_p2sh.py
evrmore/tests/test_rpc.py
evrmore/tests/test_script.py
evrmore/tests/test_scripteval.py
evrmore/tests/test_segwit.py
evrmore/tests/test_serialize.py
evrmore/tests/test_signmessage.py
evrmore/tests/test_transactions.py
evrmore/tests/test_wallet.py
python_evrmorelib-0.3.0.dist-info/licenses/LICENSE
version/__init__.py
python_evrmorelib-0.3.0.dist-info/METADATA
python_evrmorelib-0.3.0.dist-info/WHEEL
python_evrmorelib-0.3.0.dist-info/top_level.txt
python_evrmorelib-0.3.0.dist-info/RECORD
