Metadata-Version: 2.4
Name: python-evrmorelib
Version: 0.3.0
Summary: Evrmore fork of python-ravencoinlib, a fork of python-bitcoinlib
Home-page: https://github.com/standard-error/python-evrmorelib
Author: standard-error@github
Author-email: satorinetio@gmail.com
Keywords: evrmore
Classifier: Programming Language :: Python
Classifier: License :: OSI Approved :: GNU Lesser General Public License v3 or later (LGPLv3+)
License-File: LICENSE
Requires-Dist: x16r_hash
Requires-Dist: x16rv2_hash
Requires-Dist: kawpow
Requires-Dist: plyvel==1.5.1
Dynamic: author
Dynamic: author-email
Dynamic: classifier
Dynamic: description
Dynamic: description-content-type
Dynamic: home-page
Dynamic: keywords
Dynamic: license-file
Dynamic: requires-dist
Dynamic: summary
